webexsdk/__init__.py
webexsdk/_metadata.py
webexsdk/_version.py
webexsdk/config.py
webexsdk/environment.py
webexsdk/exceptions.py
webexsdk/generator_containers.py
webexsdk/response_codes.py
webexsdk/restsession.py
webexsdk/utils.py
webexsdk/api/__init__.py
webexsdk/api/access_tokens.py
webexsdk/api/admin_audit_events.py
webexsdk/api/attachment_actions.py
webexsdk/api/events.py
webexsdk/api/guest_issuer.py
webexsdk/api/licenses.py
webexsdk/api/memberships.py
webexsdk/api/messages.py
webexsdk/api/organizations.py
webexsdk/api/people.py
webexsdk/api/recordings.py
webexsdk/api/roles.py
webexsdk/api/rooms.py
webexsdk/api/team_memberships.py
webexsdk/api/teams.py
webexsdk/api/webhooks.py
webexsdk/models/__init__.py
webexsdk/models/dictionary.py
webexsdk/models/immutable.py
webexsdk/models/simple.py
webexsdk/models/cards/__init__.py
webexsdk/models/cards/actions.py
webexsdk/models/cards/adaptive_card_component.py
webexsdk/models/cards/card.py
webexsdk/models/cards/components.py
webexsdk/models/cards/container.py
webexsdk/models/cards/inputs.py
webexsdk/models/cards/options.py
webexsdk/models/cards/utils.py
webexsdk/models/mixins/__init__.py
webexsdk/models/mixins/access_token.py
webexsdk/models/mixins/admin_audit_event.py
webexsdk/models/mixins/attachment_action.py
webexsdk/models/mixins/event.py
webexsdk/models/mixins/guest_issuer_token.py
webexsdk/models/mixins/license.py
webexsdk/models/mixins/membership.py
webexsdk/models/mixins/message.py
webexsdk/models/mixins/organization.py
webexsdk/models/mixins/person.py
webexsdk/models/mixins/recording.py
webexsdk/models/mixins/role.py
webexsdk/models/mixins/room.py
webexsdk/models/mixins/room_meeting_info.py
webexsdk/models/mixins/team.py
webexsdk/models/mixins/team_membership.py
webexsdk/models/mixins/webhook.py
webexsdk/models/mixins/webhook_event.py
webexsdk-2.0.5.dist-info/LICENSE
webexsdk-2.0.5.dist-info/METADATA
webexsdk-2.0.5.dist-info/WHEEL
webexsdk-2.0.5.dist-info/top_level.txt
webexsdk-2.0.5.dist-info/RECORD
